atomqc/__init__.py
atomqc-2021.10.11.dist-info/LICENSE.md
atomqc-2021.10.11.dist-info/METADATA
atomqc-2021.10.11.dist-info/WHEEL
atomqc-2021.10.11.dist-info/top_level.txt
atomqc-2021.10.11.dist-info/RECORD
